odoo9_addon_base_partner_merge-9.0.1.0.0.99.dev38-py3.8-nspkg.pth
odoo_addons/base_partner_merge/README.rst
odoo_addons/base_partner_merge/__init__.py
odoo_addons/base_partner_merge/__openerp__.py
odoo_addons/base_partner_merge/base_partner_merge.py
odoo_addons/base_partner_merge/hooks.py
odoo_addons/base_partner_merge/validate_email.py
odoo_addons/base_partner_merge/i18n/am.po
odoo_addons/base_partner_merge/i18n/ar.po
odoo_addons/base_partner_merge/i18n/base_partner_merge.pot
odoo_addons/base_partner_merge/i18n/bg.po
odoo_addons/base_partner_merge/i18n/bs.po
odoo_addons/base_partner_merge/i18n/ca.po
odoo_addons/base_partner_merge/i18n/ca_ES.po
odoo_addons/base_partner_merge/i18n/cs.po
odoo_addons/base_partner_merge/i18n/da.po
odoo_addons/base_partner_merge/i18n/de.po
odoo_addons/base_partner_merge/i18n/el_GR.po
odoo_addons/base_partner_merge/i18n/en_AU.po
odoo_addons/base_partner_merge/i18n/en_GB.po
odoo_addons/base_partner_merge/i18n/es.po
odoo_addons/base_partner_merge/i18n/es_AR.po
odoo_addons/base_partner_merge/i18n/es_CL.po
odoo_addons/base_partner_merge/i18n/es_CO.po
odoo_addons/base_partner_merge/i18n/es_CR.po
odoo_addons/base_partner_merge/i18n/es_DO.po
odoo_addons/base_partner_merge/i18n/es_EC.po
odoo_addons/base_partner_merge/i18n/es_ES.po
odoo_addons/base_partner_merge/i18n/es_MX.po
odoo_addons/base_partner_merge/i18n/es_PE.po
odoo_addons/base_partner_merge/i18n/es_PY.po
odoo_addons/base_partner_merge/i18n/es_VE.po
odoo_addons/base_partner_merge/i18n/et.po
odoo_addons/base_partner_merge/i18n/eu.po
odoo_addons/base_partner_merge/i18n/fa.po
odoo_addons/base_partner_merge/i18n/fi.po
odoo_addons/base_partner_merge/i18n/fr.po
odoo_addons/base_partner_merge/i18n/fr_CA.po
odoo_addons/base_partner_merge/i18n/fr_CH.po
odoo_addons/base_partner_merge/i18n/fr_FR.po
odoo_addons/base_partner_merge/i18n/gl.po
odoo_addons/base_partner_merge/i18n/gl_ES.po
odoo_addons/base_partner_merge/i18n/he.po
odoo_addons/base_partner_merge/i18n/hi.po
odoo9_addon_base_partner_merge-9.0.1.0.0.99.dev38.dist-info/METADATA
odoo9_addon_base_partner_merge-9.0.1.0.0.99.dev38.dist-info/WHEEL
odoo9_addon_base_partner_merge-9.0.1.0.0.99.dev38.dist-info/namespace_packages.txt
odoo9_addon_base_partner_merge-9.0.1.0.0.99.dev38.dist-info/top_level.txt
odoo9_addon_base_partner_merge-9.0.1.0.0.99.dev38.dist-info/RECORD
